<?xml version="1.0" encoding="UTF-8" standalone="yes"?>
<destinations>
    <destination>
        <idDestination>1</idDestination>
        <idCountry>18</idCountry>
        <resort>Самый лучший курорт в Египте</resort>
        <hotel>Самый лучший отель в Египте</hotel>
        <countryByIdCountry>
            <idCountry>18</idCountry>
            <nameCountry>Египет</nameCountry>
        </countryByIdCountry>
    </destination>
    <destination>
        <idDestination>2</idDestination>
        <idCountry>19</idCountry>
        <resort>Самый лучший курорт в Турции</resort>
        <hotel>Самый лучший отель в Турции</hotel>
        <countryByIdCountry>
            <idCountry>19</idCountry>
            <nameCountry>Турция</nameCountry>
        </countryByIdCountry>
    </destination>
    <destination>
        <idDestination>3</idDestination>
        <idCountry>20</idCountry>
        <resort>Самый лучший курорт в Росии</resort>
        <hotel>Самый лучший отель в России</hotel>
        <countryByIdCountry>
            <idCountry>20</idCountry>
            <nameCountry>Россия</nameCountry>
        </countryByIdCountry>
    </destination>
</destinations>
